{
    "command_group": "az monitor app-insights component continues-export",
    "description": "Manage Continuous Export configurations for an Application Insights component.",
    "status": "GA",
    "commands": [
        {
            "name": "az monitor app-insights component continues-export create",
            "summary": "Create a Continuous Export configuration for an Application Insights component.",
            "syntax": "az monitor app-insights component continues-export create --app\n                                                          --dest-account\n                                                          --dest-container\n                                                          --dest-sas\n                                                          --dest-sub-id\n                                                          --record-types {Availability, Event, Exceptions, Messages, Metrics, PageViewPerformance, PageViews, PerformanceCounters, Rdd, Requests}\n                                                          --resource-group\n                                                          [--dest-type {Blob}]\n                                                          [--is-enabled {false, true}]",
            "required_parameters": [
                "--app -a",
                "--dest-account",
                "--dest-container",
                "--dest-sas",
                "--dest-sub-id",
                "--record-types",
                "--resource-group -g"
            ],
            "optional_parameters": [
                "--dest-type",
                "--is-enabled"
            ],
            "examples": [
                "az monitor app-insights component continues-export create -g rg \\\n--app 578f0e27-12e9-4631-bc02-50b965da2633 \\\n--record-types Requests Event Exceptions Metrics PageViews \\\n--dest-account account --dest-container container --dest-sub-id sub-id \\\n--dest-sas se=2020-10-27&sp=w&sv=2018-11-09&sr=c"
            ]
        },
        {
            "name": "az monitor app-insights component continues-export delete",
            "summary": "Delete a specific Continuous Export     configuration of an Application Insights component.",
            "syntax": "az monitor app-insights component continues-export delete --id\n                                                          [--app]\n                                                          [--ids]\n                                                          [--resource-group]\n                                                          [--subscription]\n                                                          [--yes]",
            "required_parameters": [
                "--id"
            ],
            "optional_parameters": [
                "--app -a",
                "--ids",
                "--resource-group -g",
                "--subscription",
                "--yes -y"
            ],
            "examples": [
                "az monitor app-insights component continues-export delete -g rg --app 578f0e27-12e9-4631-bc02-50b965da2633 --id exportid"
            ]
        },
        {
            "name": "az monitor app-insights component continues-export list",
            "summary": "List a list of Continuous Export configuration of an Application Insights component.",
            "syntax": "az monitor app-insights component continues-export list --app\n                                                        --resource-group",
            "required_parameters": [
                "--app -a",
                "--resource-group -g"
            ],
            "optional_parameters": [],
            "examples": [
                "az monitor app-insights component continues-export list -g rg --app 578f0e27-12e9-4631-bc02-50b965da2633"
            ]
        },
        {
            "name": "az monitor app-insights component continues-export show",
            "summary": "Get the Continuous Export configuration for this export id.",
            "syntax": "az monitor app-insights component continues-export show --id\n                                                        [--app]\n                                                        [--ids]\n                                                        [--resource-group]\n                                                        [--subscription]",
            "required_parameters": [
                "--id"
            ],
            "optional_parameters": [
                "--app -a",
                "--ids",
                "--resource-group -g",
                "--subscription"
            ],
            "examples": [
                "az monitor app-insights component continues-export show -g rg --app 578f0e27-12e9-4631-bc02-50b965da2633 --id exportid"
            ]
        },
        {
            "name": "az monitor app-insights component continues-export update",
            "summary": "Update a Continuous Export configuration for an Application Insights component.",
            "syntax": "az monitor app-insights component continues-export update --id\n                                                          [--app]\n                                                          [--dest-account]\n                                                          [--dest-container]\n                                                          [--dest-sas]\n                                                          [--dest-sub-id]\n                                                          [--dest-type {Blob}]\n                                                          [--ids]\n                                                          [--is-enabled {false, true}]\n                                                          [--record-types {Availability, Event, Exceptions, Messages, Metrics, PageViewPerformance, PageViews, PerformanceCounters, Rdd, Requests}]\n                                                          [--resource-group]\n                                                          [--subscription]",
            "required_parameters": [
                "--id"
            ],
            "optional_parameters": [
                "--app -a",
                "--dest-account",
                "--dest-container",
                "--dest-sas",
                "--dest-sub-id",
                "--dest-type",
                "--ids",
                "--is-enabled",
                "--record-types",
                "--resource-group -g",
                "--subscription"
            ],
            "examples": [
                "az monitor app-insights component continues-export update -g rg \\\n--app 578f0e27-12e9-4631-bc02-50b965da2633 \\\n--id exportid \\\n--record-types Requests Event Exceptions Metrics PageViews",
                "az monitor app-insights component continues-export update -g rg \\\n--app 578f0e27-12e9-4631-bc02-50b965da2633 \\\n--id exportid \\\n--dest-account account --dest-container container --dest-sub-id sub-id \\\n--dest-sas se=2020-10-27&sp=w&sv=2018-11-09&sr=c"
            ]
        }
    ]
}