{
    "command_group": "az cosmosdb sql restorable-database",
    "description": "Manage different versions of sql databases that are restorable in a Azure Cosmos DB account.",
    "status": "GA",
    "commands": [
        {
            "name": "az cosmosdb sql restorable-database list",
            "summary": "List all the versions of all the sql databases that were created / modified / deleted in the given restorable account.",
            "syntax": "az cosmosdb sql restorable-database list --instance-id\n                                         --location",
            "required_parameters": [
                "--instance-id -i",
                "--location -l"
            ],
            "optional_parameters": [],
            "examples": []
        }
    ]
}