{
    "command_group": "az containerapp patch",
    "description": "Patch Azure Container Apps. Patching is only available for the apps built using the source to cloud feature. See https://aka.ms/aca-local-source-to-cloud.",
    "status": "Preview",
    "commands": [
        {
            "name": "az containerapp patch apply",
            "summary": "List and apply container apps to be patched. Patching is only available for the apps built using the source to cloud feature. See https://aka.ms/aca-local-source-to-cloud.",
            "syntax": "az containerapp patch apply [--environment]\n                            [--resource-group]\n                            [--show-all]",
            "required_parameters": [],
            "optional_parameters": [
                "--environment -e",
                "--resource-group -g",
                "--show-all"
            ],
            "examples": [
                "az containerapp patch apply",
                "az containerapp patch apply -g MyResourceGroup",
                "az containerapp patch apply -g MyResourceGroup --environment MyContainerAppEnv",
                "az containerapp patch apply -g MyResourceGroup --environment MyContainerAppEnv --show-all"
            ]
        },
        {
            "name": "az containerapp patch interactive",
            "summary": "List and select container apps to be patched in an interactive way. Patching is only available for the apps built using the source to cloud feature. See https://aka.ms/aca-local-source-to-cloud.",
            "syntax": "az containerapp patch interactive [--environment]\n                                  [--resource-group]\n                                  [--show-all]",
            "required_parameters": [],
            "optional_parameters": [
                "--environment -e",
                "--resource-group -g",
                "--show-all"
            ],
            "examples": [
                "az containerapp patch interactive",
                "az containerapp patch interactive -g MyResourceGroup",
                "az containerapp patch interactive -g MyResourceGroup --environment MyContainerAppEnv",
                "az containerapp patch interactive -g MyResourceGroup --environment MyContainerAppEnv --show-all"
            ]
        },
        {
            "name": "az containerapp patch list",
            "summary": "List container apps that can be patched. Patching is only available for the apps built using the source to cloud feature. See https://aka.ms/aca-local-source-to-cloud.",
            "syntax": "az containerapp patch list [--environment]\n                           [--resource-group]\n                           [--show-all]",
            "required_parameters": [],
            "optional_parameters": [
                "--environment -e",
                "--resource-group -g",
                "--show-all"
            ],
            "examples": [
                "az containerapp patch list",
                "az containerapp patch list -g MyResourceGroup",
                "az containerapp patch list -g MyResourceGroup --environment MyContainerAppEnv",
                "az containerapp patch list -g MyResourceGroup --environment MyContainerAppEnv --show-all"
            ]
        }
    ]
}